LICENSE.txt
README.md
setup.cfg
setup.py
docs/Makefile
docs/conf.py
docs/index.rst
docs/make.bat
docs/modules.rst
docs/neural_body.rst
docs/_build/doctrees/environment.pickle
docs/_build/doctrees/index.doctree
docs/_build/doctrees/modules.doctree
docs/_build/doctrees/neural_body.doctree
docs/_build/html/.buildinfo
docs/_build/html/genindex.html
docs/_build/html/index.html
docs/_build/html/modules.html
docs/_build/html/neural_body.html
docs/_build/html/objects.inv
docs/_build/html/py-modindex.html
docs/_build/html/search.html
docs/_build/html/searchindex.js
docs/_build/html/_modules/index.html
docs/_build/html/_modules/neural_body/BenrulesRealTimeSim.html
docs/_build/html/_modules/neural_body/grav2.html
docs/_build/html/_sources/index.rst.txt
docs/_build/html/_sources/modules.rst.txt
docs/_build/html/_sources/neural_body.rst.txt
docs/_build/html/_static/alabaster.css
docs/_build/html/_static/basic.css
docs/_build/html/_static/custom.css
docs/_build/html/_static/doctools.js
docs/_build/html/_static/documentation_options.js
docs/_build/html/_static/file.png
docs/_build/html/_static/jquery-3.5.1.js
docs/_build/html/_static/jquery.js
docs/_build/html/_static/language_data.js
docs/_build/html/_static/minus.png
docs/_build/html/_static/plus.png
docs/_build/html/_static/pygments.css
docs/_build/html/_static/searchtools.js
docs/_build/html/_static/underscore-1.3.1.js
docs/_build/html/_static/underscore.js
neural_body/BenrulesRealTimeSim.py
neural_body/__init__.py
neural_body/grav2.py
neural_body.egg-info/PKG-INFO
neural_body.egg-info/SOURCES.txt
neural_body.egg-info/dependency_links.txt
neural_body.egg-info/entry_points.txt
neural_body.egg-info/requires.txt
neural_body.egg-info/top_level.txt
neural_body/__pycache__/BenrulesRealTimeSim.cpython-38.pyc
neural_body/img/sun.png
neural_body/nn/MARS-Predict-NN-Deploy-V1.02-LargeDataset_2-layer_selu_lecun-normal_mae_Adam_lr-1e-5_bs-128_epoch-350.h5
neural_body/nn/Predict-NN-Deploy-V1.02-LargeDataset_2-layer_selu_lecun-normal_mae_Adam_lr-1e-6_bs-128_epoch-250.h5
neural_body/sim_configs/mars_sim_config.csv
neural_body/sim_configs/pluto_sim_config.csv
readme_resources/adjust_speed.GIF
readme_resources/config_overview.png
