Metadata-Version: 2.1
Name: neural-body
Version: 0.1.1
Summary: An n-body simulator
Home-page: https://github.com/nedgar76/neural-body
Author: AstroGators
License: UNKNOWN
Platform: UNKNOWN
Requires-Python: >=3.8, <4
